montague_mako/__init__.py
montague_mako/mako.py
montague_mako-0.1.0.dist-info/DESCRIPTION.rst
montague_mako-0.1.0.dist-info/entry_points.txt
montague_mako-0.1.0.dist-info/METADATA
montague_mako-0.1.0.dist-info/metadata.json
montague_mako-0.1.0.dist-info/RECORD
montague_mako-0.1.0.dist-info/top_level.txt
montague_mako-0.1.0.dist-info/WHEEL
